mcp_jira/__init__.py
mcp_jira/__main__.py
mcp_jira/config.py
mcp_jira/jira_client.py
mcp_jira/mcp_protocol.py
mcp_jira/simple_mcp_server.py
mcp_jira/types.py
iflow_mcp_mcp_jira-0.1.0.dist-info/METADATA
iflow_mcp_mcp_jira-0.1.0.dist-info/WHEEL
iflow_mcp_mcp_jira-0.1.0.dist-info/entry_points.txt
iflow_mcp_mcp_jira-0.1.0.dist-info/licenses/LICENSE
iflow_mcp_mcp_jira-0.1.0.dist-info/RECORD
