Metadata-Version: 2.4
Name: iflow-mcp_mcp-jira
Version: 0.1.0
Summary: Model Context Protocol server for Jira with Scrum Master capabilities
Author: Warzuponus
License-File: LICENSE
Requires-Dist: aiohttp>=3.8.0
Requires-Dist: jira>=3.5.1
Requires-Dist: mcp>=1.0.0
Requires-Dist: pydantic-settings>=2.0.0
Requires-Dist: pydantic>=2.0.0
Requires-Dist: python-dotenv>=0.19.0
